ablerConfig/__init__.py
ablerConfig/config.py
ablerConfig-0.1.2.dist-info/METADATA
ablerConfig-0.1.2.dist-info/WHEEL
ablerConfig-0.1.2.dist-info/top_level.txt
ablerConfig-0.1.2.dist-info/RECORD
