Metadata-Version: 2.1
Name: ablerConfig
Version: 0.1.2
Summary: 配置信息处理包
Home-page: https://github.com/hanlaohan/abler-config
Author: 憨老汉
Author-email: hh28642257@gmail.com
Classifier: Development Status :: 3 - Alpha
Classifier: Intended Audience :: Developers
Classifier: License :: OSI Approved :: MIT License
Classifier: Programming Language :: Python :: 3
Classifier: Programming Language :: Python :: 3.6
Classifier: Programming Language :: Python :: 3.7
Classifier: Programming Language :: Python :: 3.8
Classifier: Programming Language :: Python :: 3.9
Classifier: Programming Language :: Python :: 3.10
Requires-Python: >=3.6
Requires-Dist: pyjson5
Requires-Dist: json5
